odoo8_addon_pos_sequence_ref_number-8.0.1.0.0.99.dev7-py3.8-nspkg.pth
odoo_addons/pos_sequence_ref_number/README.rst
odoo_addons/pos_sequence_ref_number/__init__.py
odoo_addons/pos_sequence_ref_number/__openerp__.py
odoo_addons/pos_sequence_ref_number/i18n/ca.po
odoo_addons/pos_sequence_ref_number/i18n/de.po
odoo_addons/pos_sequence_ref_number/i18n/es.po
odoo_addons/pos_sequence_ref_number/i18n/fr.po
odoo_addons/pos_sequence_ref_number/i18n/gl.po
odoo_addons/pos_sequence_ref_number/i18n/it.po
odoo_addons/pos_sequence_ref_number/i18n/nl_NL.po
odoo_addons/pos_sequence_ref_number/i18n/pos_sequence_ref_number.pot
odoo_addons/pos_sequence_ref_number/i18n/sl.po
odoo_addons/pos_sequence_ref_number/i18n/zh_CN.po
odoo_addons/pos_sequence_ref_number/models/__init__.py
odoo_addons/pos_sequence_ref_number/models/pos_order.py
odoo_addons/pos_sequence_ref_number/static/description/icon.png
odoo_addons/pos_sequence_ref_number/static/lib/moment.js
odoo_addons/pos_sequence_ref_number/static/src/js/main.js
odoo_addons/pos_sequence_ref_number/static/src/xml/pos.xml
odoo_addons/pos_sequence_ref_number/views/pos_template.xml
odoo8_addon_pos_sequence_ref_number-8.0.1.0.0.99.dev7.dist-info/METADATA
odoo8_addon_pos_sequence_ref_number-8.0.1.0.0.99.dev7.dist-info/WHEEL
odoo8_addon_pos_sequence_ref_number-8.0.1.0.0.99.dev7.dist-info/namespace_packages.txt
odoo8_addon_pos_sequence_ref_number-8.0.1.0.0.99.dev7.dist-info/top_level.txt
odoo8_addon_pos_sequence_ref_number-8.0.1.0.0.99.dev7.dist-info/RECORD
