Metadata-Version: 2.1
Name: odoo8-addon-pos-sequence-ref-number
Version: 8.0.1.0.0.99.dev7
Summary: Sequential Order numbers for Point of sale
Home-page: UNKNOWN
Author: Eficent Business and IT Consulting Services,Acsone SA/NV,Odoo Community Association (OCA)
Author-email: support@odoo-community.org
License: UNKNOWN
Platform: UNKNOWN
Classifier: Programming Language :: Python
Classifier: Framework :: Odoo
Classifier: Framework :: Odoo :: 8.0
Requires-Python: ~=2.7
Requires-Dist: odoo (<9.0a,>=8.0a)
